olostep_sdk/__init__.py
olostep_sdk/client.py
olostep_sdk/enums.py
olostep_sdk/olostep_exceptions.py
olostep_sdk/request_wrapper.py
olostep_sdk/services/__init__.py
olostep_sdk/services/batch.py
olostep_sdk/services/crawl.py
olostep_sdk/services/map.py
olostep_sdk/services/scrape.py
olostep_sdk-0.1.2.dist-info/licenses/LICENSE
olostep_sdk-0.1.2.dist-info/METADATA
olostep_sdk-0.1.2.dist-info/WHEEL
olostep_sdk-0.1.2.dist-info/top_level.txt
olostep_sdk-0.1.2.dist-info/RECORD
