Metadata-Version: 2.4
Name: olostep-sdk
Version: 0.1.2
Summary: Official Python SDK for Olostep Web Scraping API
Home-page: 
Author: Mohammad Ehsan Ansari
Author-email: mdehsan873@gmail.com
Classifier: License :: OSI Approved :: MIT License
Classifier: Programming Language :: Python :: 3
Requires-Python: >=3.7
License-File: LICENSE
Requires-Dist: requests
Dynamic: author
Dynamic: author-email
Dynamic: classifier
Dynamic: description
Dynamic: description-content-type
Dynamic: license-file
Dynamic: requires-dist
Dynamic: requires-python
Dynamic: summary
